alu.v
module alu(
    input  [7:0] A, B,
    input  [2:0] SEL,
    output reg [7:0] RESULT
);
    always @(*) begin
        case (SEL)
            3'b000: RESULT = A + B;    // ADD
            3'b001: RESULT = A - B;    // SUB
            3'b010: RESULT = A & B;    // AND
            3'b011: RESULT = A | B;    // OR
            3'b100: RESULT = B;        // MOV
            default: RESULT = 8'h00;
        endcase
    end
endmodule

reg_file.v
module reg_file (
    input clk,
    input we,
    input [2:0] rd_addr1, rd_addr2, wr_addr,
    input [7:0] wr_data,
    output [7:0] rd_data1, rd_data2
);
    reg [7:0] regs [7:0];

    assign rd_data1 = regs[rd_addr1];
    assign rd_data2 = regs[rd_addr2];

    always @(posedge clk) begin
        if (we)
            regs[wr_addr] <= wr_data;
    end
endmodule

control_unit.v
module control_unit(
    input [7:0] instr,
    output reg [2:0] opcode,
    output reg [2:0] rd,
    output reg [2:0] rs1,
    output reg [2:0] rs2,
    output reg halt
);
    always @(*) begin
        opcode = instr[7:5];
        rd     = instr[4:2];
        rs1    = instr[1:0];
        rs2    = instr[1:0];
        halt   = (opcode == 3'b111);
    end
endmodule

memory.v
module memory (
    input clk,
    input [3:0] addr,
    input [7:0] data_in,
    input we,
    output reg [7:0] data_out
);
    reg [7:0] mem [0:15];

    initial begin
        // Simple program
        // opcode | rd | rs1 | rs2
        mem[0] = 8'b000_000_01; // ADD R0 = R0 + R1
        mem[1] = 8'b001_010_11; // SUB R2 = R2 - R3
        mem[2] = 8'b010_100_01; // AND R4 = R4 & R1
        mem[3] = 8'b011_101_10; // OR  R5 = R5 | R2
        mem[4] = 8'b111_000_00; // HLT
    end

    always @(posedge clk) begin
        if (we)
            mem[addr] <= data_in;
        else
            data_out <= mem[addr];
    end
endmodule

cpu_top.v
module cpu_top(
    input clk,
    input reset
);
    reg [3:0] pc;
    wire [7:0] instr, rd_data1, rd_data2, alu_result;
    wire [2:0] opcode, rd, rs1, rs2;
    wire halt;

    // Instantiate components
    memory mem(.clk(clk), .addr(pc), .data_in(8'b0), .we(1'b0), .data_out(instr));
    control_unit cu(.instr(instr), .opcode(opcode), .rd(rd), .rs1(rs1), .rs2(rs2), .halt(halt));
    reg_file rf(.clk(clk), .we(1'b1), .rd_addr1(rs1), .rd_addr2(rs2), .wr_addr(rd),
                .wr_data(alu_result), .rd_data1(rd_data1), .rd_data2(rd_data2));
    alu alu_inst(.A(rd_data1), .B(rd_data2), .SEL(opcode), .RESULT(alu_result));

    always @(posedge clk or posedge reset) begin
        if (reset)
            pc <= 0;
        else if (!halt)
            pc <= pc + 1;
    end
endmodule

tb_cpu.sv
`timescale 1ns/1ps
module tb_cpu;
    reg clk = 0;
    reg reset = 1;

    cpu_top uut (.clk(clk), .reset(reset));

    always #5 clk = ~clk;  // 100MHz Clock

    initial begin
        $dumpfile("cpu_wave.vcd");
        $dumpvars(0, tb_cpu);
        #10 reset = 0;
        #200 $finish;
    end
endmodule

cpu_wave.vcd
$date
	Mon Oct 27 22:06:39 2025
$end
$version
	Icarus Verilog
$end
$timescale
	1ps
$end
$scope module tb_cpu $end
$var reg 1 ! clk $end
$var reg 1 " reset $end
$scope module uut $end
$var wire 1 ! clk $end
$var wire 1 " reset $end
$var wire 3 # rs2 [2:0] $end
$var wire 3 $ rs1 [2:0] $end
$var wire 8 % rd_data2 [7:0] $end
$var wire 8 & rd_data1 [7:0] $end
$var wire 3 ' rd [2:0] $end
$var wire 3 ( opcode [2:0] $end
$var wire 8 ) instr [7:0] $end
$var wire 1 * halt $end
$var wire 8 + alu_result [7:0] $end
$var reg 4 , pc [3:0] $end
$scope module alu_inst $end
$var wire 3 - SEL [2:0] $end
$var wire 8 . B [7:0] $end
$var wire 8 / A [7:0] $end
$var reg 8 0 RESULT [7:0] $end
$upscope $end
$scope module cu $end
$var wire 8 1 instr [7:0] $end
$var reg 1 * halt $end
$var reg 3 2 opcode [2:0] $end
$var reg 3 3 rd [2:0] $end
$var reg 3 4 rs1 [2:0] $end
$var reg 3 5 rs2 [2:0] $end
$upscope $end
$scope module mem $end
$var wire 4 6 addr [3:0] $end
$var wire 1 ! clk $end
$var wire 8 7 data_in [7:0] $end
$var wire 1 8 we $end
$var reg 8 9 data_out [7:0] $end
$upscope $end
$scope module rf $end
$var wire 1 ! clk $end
$var wire 3 : rd_addr1 [2:0] $end
$var wire 3 ; rd_addr2 [2:0] $end
$var wire 8 < rd_data1 [7:0] $end
$var wire 8 = rd_data2 [7:0] $end
$var wire 1 > we $end
$var wire 3 ? wr_addr [2:0] $end
$var wire 8 @ wr_data [7:0] $end
$upscope $end
$upscope $end
$upscope $end
$enddefinitions $end
$comment Show the parameter values. $end
$dumpall
$end
#0
$dumpvars
bx @
bx ?
1>
bx =
bx <
bx ;
bx :
bx 9
08
b0 7
b0 6
bx 5
bx 4
bx 3
bx 2
bx 1
bx 0
bx /
bx .
bx -
b0 ,
bx +
x*
bx )
bx (
bx '
bx &
bx %
bx $
bx #
1"
0!
$end
#5000
0*
b1 #
b1 5
b1 ;
b1 $
b1 4
b1 :
b0 '
b0 3
b0 ?
b0 (
b0 -
b0 2
b1 )
b1 1
b1 9
1!
#10000
0!
0"
#15000
b1 ,
b1 6
1!
#20000
0!
#25000
b11 #
b11 5
b11 ;
b11 $
b11 4
b11 :
b10 '
b10 3
b10 ?
b1 (
b1 -
b1 2
b101011 )
b101011 1
b101011 9
b10 ,
b10 6
1!
#30000
0!
#35000
b1 #
b1 5
b1 ;
b1 $
b1 4
b1 :
b100 '
b100 3
b100 ?
b10 (
b10 -
b10 2
b1010001 )
b1010001 1
b1010001 9
b11 ,
b11 6
1!
#40000
0!
#45000
b10 #
b10 5
b10 ;
b10 $
b10 4
b10 :
b101 '
b101 3
b101 ?
b11 (
b11 -
b11 2
b1110110 )
b1110110 1
b1110110 9
b100 ,
b100 6
1!
#50000
0!
#55000
b0 +
b0 0
b0 @
1*
b0 #
b0 5
b0 ;
b0 $
b0 4
b0 :
b0 '
b0 3
b0 ?
b111 (
b111 -
b111 2
b11100000 )
b11100000 1
b11100000 9
b101 ,
b101 6
1!
#60000
0!
#65000
x*
b0xx #
b0xx 5
b0xx ;
b0xx $
b0xx 4
b0xx :
bx '
bx 3
bx ?
bx (
bx -
bx 2
bx )
bx 1
bx 9
bx &
bx /
bx <
bx %
bx .
bx =
1!
